CHANGES.rst
MANIFEST.in
README.rst
setup.cfg
setup.py
kotti_multilingual/__init__.py
kotti_multilingual/api.py
kotti_multilingual/events.py
kotti_multilingual/patches.py
kotti_multilingual/resources.py
kotti_multilingual/sqla.py
kotti_multilingual/widget.py
kotti_multilingual.egg-info/PKG-INFO
kotti_multilingual.egg-info/SOURCES.txt
kotti_multilingual.egg-info/dependency_links.txt
kotti_multilingual.egg-info/not-zip-safe
kotti_multilingual.egg-info/requires.txt
kotti_multilingual.egg-info/top_level.txt
kotti_multilingual/locale/README
kotti_multilingual/locale/kotti_multilingual.pot
kotti_multilingual/locale/de/LC_MESSAGES/kotti_multilingual.mo
kotti_multilingual/locale/de/LC_MESSAGES/kotti_multilingual.po
kotti_multilingual/templates/language-dropdown.pt
kotti_multilingual/templates/language-selection.pt
kotti_multilingual/templates/translation-dropdown.pt
kotti_multilingual/tests/conftest.py
kotti_multilingual/tests/test_api.py
kotti_multilingual/tests/test_configure.py
kotti_multilingual/tests/test_events.py
kotti_multilingual/tests/test_linkaction.py
kotti_multilingual/tests/test_resources.py
kotti_multilingual/tests/test_sqla.py
kotti_multilingual/tests/test_translate.py
kotti_multilingual/tests/test_views.py
kotti_multilingual/tests/test_widget.py
kotti_multilingual/views/__init__.py
kotti_multilingual/views/actions.py
kotti_multilingual/views/content.py
kotti_multilingual/views/language_selection.py
kotti_multilingual/views/translate.py
kotti_multilingual/views/util.py