Metadata-Version: 1.1
Name: kotti-multilingual
Version: 0.2a3
Summary: Multilangual sites with Kotti
Home-page: https://github.com/Kotti/kotti_multilingual
Author: Andreas Kaiser
Author-email: disko@binary-punks.com
License: BSD
Keywords: kotti add-on
Platform: UNKNOWN
Classifier: Environment :: Web Environment
Classifier: Framework :: Pylons
Classifier: Framework :: Pyramid
Classifier: Intended Audience :: Developers
Classifier: License :: OSI Approved :: BSD License
Classifier: Operating System :: OS Independent
Classifier: Programming Language :: Python
Classifier: Programming Language :: Python :: 2.6
Classifier: Programming Language :: Python :: 2.7
Classifier: Topic :: Internet :: WWW/HTTP
Classifier: Topic :: Software Development :: User Interfaces
